{
  "version": "5",
  "dialect": "mysql",
  "id": "9c66ec0a-04f5-43f5-a940-6474972c7548",
  "prevId": "00000000-0000-0000-0000-000000000000",
  "tables": {
    "folders": {
      "name": "folders",
      "columns": {
        "id": {
          "name": "id",
          "type": "int",
          "primaryKey": false,
          "notNull": true,
          "autoincrement": true
        },
        "name": {
          "name": "name",
          "type": "varchar(255)",
          "primaryKey": false,
          "notNull": true,
          "autoincrement": false
        },
        "parent_id": {
          "name": "parent_id",
          "type": "int",
          "primaryKey": false,
          "notNull": false,
          "autoincrement": false
        },
        "created_at": {
          "name": "created_at",
          "type": "timestamp",
          "primaryKey": false,
          "notNull": false,
          "autoincrement": false,
          "default": "(now())"
        },
        "updated_at": {
          "name": "updated_at",
          "type": "timestamp",
          "primaryKey": false,
          "notNull": false,
          "autoincrement": false,
          "default": "(now())"
        }
      },
      "indexes": {},
      "foreignKeys": {},
      "compositePrimaryKeys": {
        "folders_id": {
          "name": "folders_id",
          "columns": [
            "id"
          ]
        }
      },
      "uniqueConstraints": {},
      "checkConstraint": {}
    }
  },
  "views": {},
  "_meta": {
    "schemas": {},
    "tables": {},
    "columns": {}
  },
  "internal": {
    "tables": {},
    "indexes": {}
  }
}